actio/__init__.py
actio/actor.py
actio/cluster.py
actio/config.py
actio/crush.py
actio/messages.py
actio/ref.py
actio/registry.py
actio-0.1.3.dist-info/METADATA
actio-0.1.3.dist-info/WHEEL
actio-0.1.3.dist-info/licenses/LICENSE
actio-0.1.3.dist-info/RECORD
