Metadata-Version: 2.4
Name: actio
Version: 0.1.3
Summary: Pure Python actor system for building concurrent and distributed applications with async/await support for Python 3.11+
License: MIT
License-File: LICENSE
Author: Semenets V. Pavel
Author-email: p.semenets@gmail.com
Requires-Python: >=3.11
Classifier: Development Status :: 4 - Beta
Classifier: Intended Audience :: Developers
Classifier: License :: OSI Approved :: MIT License
Classifier: Operating System :: OS Independent
Classifier: Programming Language :: Python :: 3
Classifier: Programming Language :: Python :: 3.11
Classifier: Programming Language :: Python :: 3.12
Classifier: Programming Language :: Python :: 3.13
Classifier: Programming Language :: Python :: 3.14
Classifier: Topic :: Communications
Classifier: Topic :: Software Development :: Libraries
Classifier: Topic :: System :: Hardware
Requires-Dist: pydantic (>=2.12.4,<3.0.0)
Project-URL: Documentation, https://github.com/xDarkmanx/actio#readme
Project-URL: Homepage, https://github.com/xDarkmanx/actio
Project-URL: Repository, https://github.com/xDarkmanx/actio
